Workbook

Sheet PT320_Materialidade
A1: PT 320 – Materialidade (R$ mil) – amarelo = entrada (NE 2025 / julgamento do aluno)
A3: Lucro antes do IR/CS 2025 consolidado (NE 6(b)) | B3: 1878987
A4: (-) Ganho líquido na venda do Midway Mall, antes dos tributos (NE 5.3) | B4: 1204894
A5: LAIR normalizado (não recorrente excluído) | B5: =B3-B4 -> 674093
A7: Benchmark | B7: Base (R$ mil) | C7: % | D7: Resultado (R$ mil)
A8: LAIR normalizado (ESCOLHIDO) | B8: =B5 -> 674093 | C8: 0.05 | D8: =B8*C8 -> 33704.65
A9: LAIR reportado (referência) | B9: =B3 -> 1878987 | C9: 0.05 | D9: =B9*C9 -> 93949.35
A10: Receita líquida 2025 (NE 6) | B10: 10497046 | C10: 0.005 | D10: =B10*C10 -> 52485.23
A11: Ativo total 2025 (NE 6) | B11: 14872670 | C11: 0.005 | D11: =B11*C11 -> 74363.35
A12: LAIR 2024 (NE 6) | B12: 361945 | C12: 0.05 | D12: =B12*C12 -> 18097.25
A14: Materialidade global (PM) – arredondada a R$ 100 mil | B14: =ROUND(D8,-2) -> 33700
A15: % de execução | B15: 0.75
A16: Materialidade para execução (PE) | B16: =B14*B15 -> 25275
A17: % limite de acumulação de distorções claramente triviais | B17: 0.05
A18: Limite de distorções claramente triviais | B18: =B14*B17 -> 1685
A20: PM como % do LAIR reportado | B20: =B14/B3 -> 0.017935196
A21: PM como % da receita líquida | B21: =B14/B10 -> 0.003210427
A22: PM como % do saldo líquido de contas a receber (5.478.486) | B22: =B14/5478486 -> 0.0061513345

Sheet PT540_Sensibilidade_ECL
A1: PT 540 – Sensibilidade da estimativa de perdas esperadas (NE 13(g)) – R$ mil
A3: Estágio | B3: Bruto 31/12/25 | C3: Provisão 31/12/25 | D3: Cobertura 2025 | E3: Bruto 31/12/24 | F3: Provisão 31/12/24 | G3: Cobertura 2024 | H3: Δ cobertura (pp)
A4: 1 | B4: 4679473 | C4: 209602 | D4: =C4/B4 -> 0.044791796 | E4: 4600923 | F4: 301050 | G4: =F4/E4 -> 0.065432523 | H4: =(D4-G4)*100 -> -2.0640727
A5: 2 | B5: 179402 | C5: 53537 | D5: =C5/B5 -> 0.29841919 | E5: 236887 | F5: 59247 | G5: =F5/E5 -> 0.25010659 | H5: =(D5-G5)*100 -> 4.8312602
A6: 3 | B6: 1757287 | C6: 1322917 | D6: =C6/B6 -> 0.75281784 | E6: 880584 | F6: 644990 | G6: =F6/E6 -> 0.7324571 | H6: =(D6-G6)*100 -> 2.0360741
A7: Total | B7: =SUM(B4:B6) -> 6616162 | C7: =SUM(C4:C6) -> 1586056 | D7: =C7/B7 -> 0.23972448 | E7: =SUM(E4:E6) -> 5718394 | F7: =SUM(F4:F6) -> 1005287 | G7: =F7/E7 -> 0.17579883
A9: Cenários (efeito na provisão = bruto × Δ cobertura; positivo = provisão adicional)
A10: Cenário | B10: Δ cobertura aplicada | C10: Efeito (R$ mil) | D10: Efeito / PM | E10: Efeito / PE
A11: Estágio 1 volta à cobertura do comparativo 2024 (re-apresentado na DFP 2025; não comparável com níveis A–H originais) | B11: =G4-D4 -> 0.020640727 | C11: =B11*B4 -> 96587.725 | D11: =C11/PT320_Materialidade!$B$14 -> 2.8661046 | E11: =C11/PT320_Materialidade!$B$16 -> 3.8214728
A12: Estágio 3 -5 pp de cobertura | B12: -0.05 | C12: =B12*B6 -> -87864.35 | D12: =C12/PT320_Materialidade!$B$14 -> -2.6072507 | E12: =C12/PT320_Materialidade!$B$16 -> -3.4763343
A13: Estágio 3 +5 pp de cobertura | B13: 0.05 | C13: =B13*B6 -> 87864.35 | D13: =C13/PT320_Materialidade!$B$14 -> 2.6072507 | E13: =C13/PT320_Materialidade!$B$16 -> 3.4763343
A14: Estágio 2 -5 pp de cobertura | B14: -0.05 | C14: =B14*B5 -> -8970.1 | D14: =C14/PT320_Materialidade!$B$14 -> -0.26617507 | E14: =C14/PT320_Materialidade!$B$16 -> -0.3549001
A15: Estágio 2 +5 pp | B15: 0.05 | C15: =B15*B5 -> 8970.1 | D15: =C15/PT320_Materialidade!$B$14 -> 0.26617507 | E15: =C15/PT320_Materialidade!$B$16 -> 0.3549001
A16: Cobertura TOTAL da Midway ±1 pp (não depende da alocação por estágio) | B16: 0.01 | C16: =B16*B7 -> 66161.62 | D16: =C16/PT320_Materialidade!$B$14 -> 1.9632528 | E16: =C16/PT320_Materialidade!$B$16 -> 2.6176704
A17: Combinado: E1 volta a 2024 + E3 -2 pp | C17: =C11+(-0.02*B6) -> 61441.985 | D17: =C17/PT320_Materialidade!$B$14 -> 1.8232043
A18: Cobertura total Midway: 2024 original (DFP 2024) 17,58% = 1.005.287/5.718.394; 2025 = 23,97% = 1.586.056/6.616.161

Sheet PT520_Analiticos
A1: PT 520 – Procedimentos analíticos substantivos (dados REAIS das NE 2025, R$ mil)
A3: Indicador | B3: 2025 | C3: 2024 | D3: Variação % | E3: Expectativa 2025 | F3: Diferença | G3: Limite de investigação (PE) | H3: Investigar?
A4: Receita de operações de crédito (NE 33) | B4: 2454777 | C4: 2238120 | D4: =B4/C4-1 -> 0.09680312 | E4: =C4*(B5/C5) -> 2589657.9 | F4: =B4-E4 -> -134880.9 | G4: =PT320_Materialidade!$B$16 -> 25275 | H4: =IF(ABS(F4)>G4,"SIM","NÃO") -> SIM
A5: Carteira Midway: cartão + crédito pessoal (NE 13a) | B5: 6616161 | C5: 5718038 | D5: =B5/C5-1 -> 0.15706839
A6: Contas a receber bruto (NE 13a) | B6: 7065501 | C6: 6117786 | D6: =B6/C6-1 -> 0.15491143
A7: Saldo vencido (NE 13d) | B7: 1970663 | C7: 895053 | D7: =B7/C7-1 -> 1.2017277
A8: Provisão para perdas (ECL) (NE 13f) | B8: 1587015 | C8: 1006059 | D8: =B8/C8-1 -> 0.57745719
A9: Baixas para perda no ano (NE 13f) | B9: 272324 | C9: 971639 | D9: =B9/C9-1 -> -0.71972718
A10: Despesa ECL (NE 34.2) | B10: 845004 | C10: 794613 | D10: =B10/C10-1 -> 0.063415776
A11: Estoques – provisão para perdas (NE 14b) | B11: 143085 | C11: 86035 | D11: =B11/C11-1 -> 0.66310223
A12: Receita líquida (NE 33) | B12: 10497046 | C12: 9634207 | D12: =B12/C12-1 -> 0.08955994
A13: Custo dos produtos/mercad. e serviços (NE 34.1) | B13: 4114271 | C13: 3952420 | D13: =B13/C13-1 -> 0.040949848
A15: Razões
A16: Razão | B16: 2025 | C16: 2024 | D16: Δ (pp)
A17: ECL / carteira bruta | B17: =B8/B6 -> 0.22461465 | C17: =C8/C6 -> 0.16444822 | D17: =(B17-C17)*100 -> 6.0166428
A18: Vencido / carteira bruta | B18: =B7/B6 -> 0.27891341 | C18: =C7/C6 -> 0.14630342 | D18: =(B18-C18)*100 -> 13.261
A19: Baixas / ECL inicial | B19: =B9/C8 -> 0.27068393
A20: Provisão estoques / estoques bruto (NE 14: 143.085 / 1.752.648; 86.035 / 1.547.476) | B20: =143085/(1609563+143085) -> 0.081639325 | C20: =86035/(1461441+86035) -> 0.055596985 | D20: =(B20-C20)*100 -> 2.604234
A21: Margem bruta (consolidada) | B21: =(B12-B13)/B12 -> 0.6080544 | C21: =(C12-C13)/C12 -> 0.58975139 | D21: =(B21-C21)*100 -> 1.8303006
A23: Expectativa da receita de crédito = receita 2024 × crescimento da carteira Midway (fim de ano). Limite de investigação = PE.
A24: Reconciliação EBITDA (NE 4.2): lucro + IR/CS + resultado financeiro + D&A | B24: =1475168+403819+496741+758497 -> 3134225 | C24: 3134225 | D24: =B24-C24 -> 0

Sheet PT500_Conciliacao_NE13
A1: bloco | B1: item | C1: ne_2025_mil | D1: base_sintetica_mil | E1: diferenca_mil
A2: produto | B2: CARTAO_RIACHUELO | C2: 5730153 | D2: 5773466.9 | E2: =D2-C2 -> 43313.906
A3: produto | B3: CREDITO_PESSOAL | C3: 886008 | D3: 887086.64 | E3: =D3-C3 -> 1078.644
A4: produto | B4: CARTAO_TERCEIROS | C4: 386955 | D4: 386955 | E4: =D4-C4 -> 0
A5: produto | B5: CESSAO_FIDC | C5: 50461 | D5: 50461 | E5: =D5-C5 -> 0
A6: produto | B6: OUTROS_VALORES | C6: 50396 | D6: 50396 | E6: =D6-C6 -> 0
A7: ajuste | B7: PROVISAO_LIMITE_A_LIBERAR | C7: -34104 | D7: -34104 | E7: =D7-C7 -> 0
A8: ajuste | B8: AVP | C8: -4368 | D8: -4368 | E8: =D8-C8 -> 0
A9: aging | B9: A_VENCER | C9: 5094838 | D9: 5128430.5 | E9: =D9-C9 -> 33592.55
A10: aging | B10: ATE_30 | C10: 145437 | D10: 145437 | E10: =D10-C10 -> 0
A11: aging | B11: 31_60 | C11: 90881 | D11: 90881 | E11: =D11-C11 -> 0
A12: aging | B12: 61_90 | C12: 110037 | D12: 110037 | E12: =D12-C12 -> 0
A13: aging | B13: 91_180 | C13: 380520 | D13: 380520 | E13: =D13-C13 -> 0
... A21: ECL estágio | B21: Estágio 3 | C21: 1322917 | D21: 1298890.8 | E21: =D21-C21 -> -24026.209

Sheet PT450_Erros_x_Testes
A1: id_erro | B1: teste | C1: inseridos | D1: sinalizados | E1: identificados | F1: recall_pct | G1: falsos_positivos | H1: distorcao_liquida_inserida_mil
A2: E05 | B2: T02_vencimento_antes_origem | C2: 400 | D2: 400 | E2: 400 | F2: 100 | G2: 0 | H2: 0
A3: E01 | B3: T03_corte_origem_pos_2025 | C3: 1100 | D3: 1100 | E3: 1100 | F3: 100 | G3: 0 | H3: 14800
A4: E04 | B4: T04_duplicidade_contrato | C4: 660 | D4: 1320 | E4: 660 | F4: 100 | G4: 660 | H4: 9131.2
A5: E02 | B5: T05_estagio_incoerente_atraso | C5: 2500 | D5: 2500 | E5: 2500 | F5: 100 | G5: 0 | H5: 25667.3
A6: E03 | B6: T06_estagio3_provisao_baixa | C6: 600 | D6: 600 | E6: 600 | F6: 100 | G6: 0 | H6: 7195.9
A7: E06 | B7: T07_titulo_acima_541_dias | C7: 800 | D7: 800 | E7: 800 | F7: 100 | G7: 0 | H7: 540
A8: E07 | B8: T08_manual_redondo_fim_periodo | C8: 60 | D8: 60 | E8: 60 | F8: 100 | G8: 0 | H8: 9200
A9: TOTAL | C9: =SUM(C2:C8) -> 6120 | E9: =SUM(E2:E8) -> 6120 | H9: =SUM(H2:H8) -> 66534.4
A10: Distorção líquida total / PM | H10: =H9/PT320_Materialidade!B14 -> 1.9743145

Sheet PT530_MUS
A1: PT 530 – Amostragem por Unidade Monetária (base SINTÉTICA)
A3: Valor contábil da população (R$ mil) | B3: 7148365.5
A4: Erro tolerável = PE (R$ mil) | B4: =PT320_Materialidade!B16 -> 25275
A5: Fator de confiança 95% (Poisson, 0 erros) | B5: 3
A6: Erro esperado (% do tolerável) | B6: 0.1
A7: Fator de expansão | B7: 1.6
A9: Intervalo de amostragem (R$ mil) | B9: =(B4-B6*B4*B7)/B5 -> 7077
A10: Tamanho teórico da amostra | B10: =B3/B9 -> 1010.0841
A12: Itens selecionados | B12: 1010
A13: Itens com distorção | B13: 17
A14: Distorção projetada (R$ mil) | B14: 93866.4
A15: Limite superior Stringer (R$ mil) | B15: 148273.7
A16: Distorção real inserida (R$ mil) | B16: 66534.4
A17: Conclusão | B17: REJEITAR (limite superior > erro tolerável)
